Workbook

Sheet Cover
A1: India UPI MDR revenue pool: sizing model
A2: Prepared by Aditya Mathur, October 2026. Independent work, not affiliated with Redseer, NPCI or any company named.
A4: Question
A5: From 15 Oct 2026, merchants pay 0.4% MDR on UPI P2M payments above ₹2,000, with exemptions. How large is the annual revenue pool, how much do the exemptions remove, and which assumptions matter most?
A7: How to use
A8: 1. Inputs: blue cells are inputs. Yellow cells are the key assumptions to test in primary research. Pick the scenario in Inputs!C3 (1 = Base, 2 = Conservative, 3 = Upside).
A9: 2. Model: the waterfall from gross to net for the selected scenario, and the headline outputs.
A10: 3. Cases: every scenario and sensitivity case as one row, each computing the net pool from its own inputs.
A11: 4. Sensitivity: one-at-a-time swings on the net pool, ranked (the tornado).
A13: Units
A14: Payment value in ₹ lakh crore. Revenue in ₹ crore (1 lakh crore = 1,00,000 crore). Revenue is an FY27 annualised run-rate unless labelled part-year.
A16: Colour legend
... A22: Business Standard, 16 Sep 2026: 0.4% MDR above ₹2,000 from 15 Oct; ₹300 cap at ₹75,000+; ₹5 flat for essential services; 0.02% for capital markets; small merchants up to ₹1 lakh/month and rural/semi-urban QR exempt; 5% to an acceptance fund; FY27 incentive ₹2,000 crore; industry P2M cost ~₹20,700 crore a year.

Sheet Inputs
A1: Inputs
A3: Selected scenario (1 Base, 2 Conservative, 3 Upside) | C3: 1 | D3: =INDEX({"Base","Conservative","Upside"},1,C3) -> Base
A4: Input | B4: Base | C4: Conservative | D4: Upside | E4: Unit | F4: Source / note
A5: UPI value, FY26 | B5: 314 | C5: 314 | D5: 314 | E5: ₹ lakh crore | F5: PIB, Aug 2026
A6: P2M share of UPI value | B6: 0.29 | C6: 0.29 | D6: 0.29 | E6: % | F6: PIB: P2P is 71% of value
A7: Share of P2M value above ₹2,000 | B7: 0.66 | C7: 0.66 | D7: 0.66 | E7: % | F7: IIM Bangalore, June 2025 data
A8: FY27 value growth | B8: 0.2 | C8: 0.15 | D8: 0.24 | E8: % | F8: Assumption; FY26 grew 21% (PIB)
A9: MDR rate | B9: 0.004 | C9: 0.004 | D9: 0.004 | E9: % | F9: NPCI, from 15 Oct 2026
A10: Small merchants exempt (share of above-₹2,000 P2M value) | B10: 0.12 | C10: 0.18 | D10: 0.08 | E10: % | F10: Assumption: up to ₹1 lakh/month on QR
A11: Rural and semi-urban QR exempt (share) | B11: 0.08 | C11: 0.12 | D11: 0.05 | E11: % | F11: Assumption
A12: Essential services at ₹5 flat (share) | B12: 0.15 | C12: 0.2 | D12: 0.1 | E12: % | F12: Assumption: railways, telecom, fuel, insurance
A13: Essential services average ticket | B13: 4000 | C13: 4000 | D13: 4000 | E13: ₹ | F13: Assumption
A14: Capital markets at 0.02% (share) | B14: 0.15 | C14: 0.2 | D14: 0.1 | E14: % | F14: Assumption: mutual funds and broking
A15: Capital markets rate | B15: 0.0002 | C15: 0.0002 | D15: 0.0002 | E15: % | F15: NPCI
A16: Standard value in ₹75,000+ payments (₹300 cap) | B16: 0.15 | C16: 0.2 | D16: 0.1 | E16: % | F16: Assumption
... A22: Budget incentive, FY27 | B22: 2000 | C22: 2000 | D22: 2000 | E22: ₹ crore | F22: Union Budget, via Business Standard
A24: Check: exempt + special shares must not exceed 100% in any scenario | B24: =IF(B10+B11+B12+B14<=1,"OK","CHECK") -> OK | C24: =IF(C10+C11+C12+C14<=1,"OK","CHECK") -> OK | D24: =IF(D10+D11+D12+D14<=1,"OK","CHECK") -> OK

Sheet Model
A1: Model: selected scenario
A2: ="Scenario: "&Inputs!D3 -> Scenario: Base
A4: Line | B4: Value | C4: Unit | D4: How it is calculated
A5: UPI value, FY26 | B5: =INDEX(Inputs!$B$5:$D$5,1,Inputs!$C$3) -> 314 | C5: ₹ lakh crore | D5: Input
A6: P2M value, FY26 | B6: =B5*INDEX(Inputs!$B$6:$D$6,1,Inputs!$C$3) -> 91.06 | C6: ₹ lakh crore | D6: UPI value × P2M share
A7: P2M value above ₹2,000, FY26 | B7: =B6*INDEX(Inputs!$B$7:$D$7,1,Inputs!$C$3) -> 60.0996 | C7: ₹ lakh crore | D7: × share above ₹2,000
A8: P2M value above ₹2,000, FY27 annualised | B8: =B7*(1+INDEX(Inputs!$B$8:$D$8,1,Inputs!$C$3)) -> 72.11952 | C8: ₹ lakh crore | D8: × (1 + growth)
A9: Same, in ₹ crore | B9: =B8*100000 -> 7211952 | C9: ₹ crore | D9: × 1,00,000
A10: Standard merchant share | B10: =MAX(0,1-INDEX(Inputs!$B$10:$D$10,1,Inputs!$C$3)-INDEX(Inputs!$B$11:$D$11,1,Inputs!$C$3)-INDEX(Inputs!$B$12:$D$12,1,Inputs!$C$3)-INDEX(Inputs!$B$14:$D$14,1,Inputs!$C$3)) -> 0.5 | C10: % | D10: 1 − exempt and special shares
A11: Capped effective rate | B11: =MIN(INDEX(Inputs!$B$9:$D$9,1,Inputs!$C$3),300/INDEX(Inputs!$B$17:$D$17,1,Inputs!$C$3)) -> 0.002 | C11: % | D11: ₹300 ÷ average capped ticket
A13: Waterfall (₹ crore, FY27 run-rate)
A14: Gross: 0.4% on all P2M above ₹2,000 | B14: =B9*INDEX(Inputs!$B$9:$D$9,1,Inputs!$C$3) -> 28847.808 | C14: ₹ crore | D14: Base × MDR
A15: Small-merchant exemption | B15: =-B9*INDEX(Inputs!$B$10:$D$10,1,Inputs!$C$3)*INDEX(Inputs!$B$9:$D$9,1,Inputs!$C$3) -> -3461.737 | C15: ₹ crore | D15: Exempt share × MDR
A16: Rural and semi-urban exemption | B16: =-B9*INDEX(Inputs!$B$11:$D$11,1,Inputs!$C$3)*INDEX(Inputs!$B$9:$D$9,1,Inputs!$C$3) -> -2307.8246 | C16: ₹ crore | D16: Exempt share × MDR
A17: Essential services at ₹5 flat | B17: =B9*INDEX(Inputs!$B$12:$D$12,1,Inputs!$C$3)*(5/INDEX(Inputs!$B$13:$D$13,1,Inputs!$C$3)-INDEX(Inputs!$B$9:$D$9,1,Inputs!$C$3)) -> -2974.9302 | C17: ₹ crore | D17: Share × (₹5 ÷ ticket − MDR)
A18: Capital markets at 0.02% | B18: =B9*INDEX(Inputs!$B$14:$D$14,1,Inputs!$C$3)*(INDEX(Inputs!$B$15:$D$15,1,Inputs!$C$3)-INDEX(Inputs!$B$9:$D$9,1,Inputs!$C$3)) -> -4110.8126 | C18: ₹ crore | D18: Share × (0.02% − MDR)
A19: ₹300 cap on ₹75,000+ payments | B19: =-B9*B10*(1-INDEX(Inputs!$B$18:$D$18,1,Inputs!$C$3))*INDEX(Inputs!$B$16:$D$16,1,Inputs!$C$3)*(INDEX(Inputs!$B$9:$D$9,1,Inputs!$C$3)-B11) -> -1027.7032 | C19: ₹ crore | D19: Standard × capped share × (MDR − capped rate)
A20: Leakage to other rails | B20: =-B9*B10*INDEX(Inputs!$B$18:$D$18,1,Inputs!$C$3)*INDEX(Inputs!$B$9:$D$9,1,Inputs!$C$3) -> -721.1952 | C20: ₹ crore | D20: Standard × leakage × MDR
A21: Net revenue pool | B21: =SUM(B14:B20) -> 14243.605 | C21: ₹ crore | D21: Sum of the waterfall
A23: Headline outputs
A24: Net pool as % of gross | B24: =IF(B14=0,0,B21/B14) -> 0.49375 | C24: %
A25: Effective MDR on above-₹2,000 P2M value | B25: =IF(B9=0,0,B21/B9) -> 0.001975 | C25: %
A26: FY27 part-year revenue | B26: =B21*INDEX(Inputs!$B$20:$D$20,1,Inputs!$C$3)/12 -> 6528.3191 | C26: ₹ crore | D26: Run-rate × months ÷ 12
A27: To small-merchant acceptance fund | B27: =B21*INDEX(Inputs!$B$19:$D$19,1,Inputs!$C$3) -> 712.18026 | C27: ₹ crore | D27: 5% of net
A28: Left for ecosystem participants | B28: =B21-B27 -> 13531.425 | C28: ₹ crore | D28: Split not published by NPCI
A29: Share of industry P2M cost covered | B29: =IF(INDEX(Inputs!$B$21:$D$21,1,Inputs!$C$3)=0,0,B21/INDEX(Inputs!$B$21:$D$21,1,Inputs!$C$3)) -> 0.68809687 | C29: % | D29: Net ÷ ₹20,700 crore
A30: Multiple of FY27 budget incentive | B30: =IF(INDEX(Inputs!$B$22:$D$22,1,Inputs!$C$3)=0,0,B21/INDEX(Inputs!$B$22:$D$22,1,Inputs!$C$3)) -> 7.1218026 | C30: x | D30: Net ÷ ₹2,000 crore
A31: Cost to a standard merchant per ₹100 crore of above-₹2,000 UPI sales | B31: =100*INDEX(Inputs!$B$9:$D$9,1,Inputs!$C$3)*100 -> 40 | C31: ₹ lakh | D31: ₹100 crore × MDR, in lakh
A32: Check: waterfall equals direct calculation | B32: =IF(ABS(B21-Cases!T5)<1,"OK","CHECK") -> OK

Sheet Cases
A1: Cases: every scenario and sensitivity run, one row each
A2: Each row computes the net pool from its own inputs. Sensitivity rows copy Base and change one input (blue).
A4: Case | B4: UPI value FY26 | C4: P2M share | D4: Above ₹2,000 share | E4: Growth | F4: MDR | G4: Small merchant | H4: Rural | I4: Essential | J4: Essential ticket | K4: Capital markets | L4: Cap mkt rate | M4: Capped share | N4: Capped ticket | O4: Leakage | P4: Above-₹2,000 value FY27 (₹ crore) | Q4: Gross (₹ crore) | R4: Standard share | S4: Capped rate | T4: Net pool (₹ crore)
A5: Selected scenario | B5: =INDEX(Inputs!$B$5:$D$5,1,Inputs!$C$3) -> 314 | C5: =INDEX(Inputs!$B$6:$D$6,1,Inputs!$C$3) -> 0.29 | D5: =INDEX(Inputs!$B$7:$D$7,1,Inputs!$C$3) -> 0.66 | E5: =INDEX(Inputs!$B$8:$D$8,1,Inputs!$C$3) -> 0.2 | F5: =INDEX(Inputs!$B$9:$D$9,1,Inputs!$C$3) -> 0.004 | G5: =INDEX(Inputs!$B$10:$D$10,1,Inputs!$C$3) -> 0.12 | H5: =INDEX(Inputs!$B$11:$D$11,1,Inputs!$C$3) -> 0.08 | I5: =INDEX(Inputs!$B$12:$D$12,1,Inputs!$C$3) -> 0.15 | J5: =INDEX(Inputs!$B$13:$D$13,1,Inputs!$C$3) -> 4000 | K5: =INDEX(Inputs!$B$14:$D$14,1,Inputs!$C$3) -> 0.15 | L5: =INDEX(Inputs!$B$15:$D$15,1,Inputs!$C$3) -> 0.0002 | M5: =INDEX(Inputs!$B$16:$D$16,1,Inputs!$C$3) -> 0.15 | N5: =INDEX(Inputs!$B$17:$D$17,1,Inputs!$C$3) -> 150000 | O5: =INDEX(Inputs!$B$18:$D$18,1,Inputs!$C$3) -> 0.05 | P5: =B5*C5*D5*(1+E5)*100000 -> 7211952 | Q5: =P5*F5 -> 28847.808 | R5: =MAX(0,1-G5-H5-I5-K5) -> 0.5 | S5: =MIN(F5,300/N5) -> 0.002 | T5: =P5*(I5*5/J5+K5*L5+R5*(1-O5)*((1-M5)*F5+M5*S5)) -> 14243.605
A6: Base | B6: =Inputs!B5 -> 314 | C6: =Inputs!B6 -> 0.29 | D6: =Inputs!B7 -> 0.66 | E6: =Inputs!B8 -> 0.2 | F6: =Inputs!B9 -> 0.004 | G6: =Inputs!B10 -> 0.12 | H6: =Inputs!B11 -> 0.08 | I6: =Inputs!B12 -> 0.15 | J6: =Inputs!B13 -> 4000 | K6: =Inputs!B14 -> 0.15 | L6: =Inputs!B15 -> 0.0002 | M6: =Inputs!B16 -> 0.15 | N6: =Inputs!B17 -> 150000 | O6: =Inputs!B18 -> 0.05 | P6: =B6*C6*D6*(1+E6)*100000 -> 7211952 | Q6: =P6*F6 -> 28847.808 | R6: =MAX(0,1-G6-H6-I6-K6) -> 0.5 | S6: =MIN(F6,300/N6) -> 0.002 | T6: =P6*(I6*5/J6+K6*L6+R6*(1-O6)*((1-M6)*F6+M6*S6)) -> 14243.605
A7: Conservative | B7: =Inputs!C5 -> 314 | C7: =Inputs!C6 -> 0.29 | D7: =Inputs!C7 -> 0.66 | E7: =Inputs!C8 -> 0.15 | F7: =Inputs!C9 -> 0.004 | G7: =Inputs!C10 -> 0.18 | H7: =Inputs!C11 -> 0.12 | I7: =Inputs!C12 -> 0.2 | J7: =Inputs!C13 -> 4000 | K7: =Inputs!C14 -> 0.2 | L7: =Inputs!C15 -> 0.0002 | M7: =Inputs!C16 -> 0.2 | N7: =Inputs!C17 -> 150000 | O7: =Inputs!C18 -> 0.1 | P7: =B7*C7*D7*(1+E7)*100000 -> 6911454 | Q7: =P7*F7 -> 27645.816 | R7: =MAX(0,1-G7-H7-I7-K7) -> 0.3 | S7: =MIN(F7,300/N7) -> 0.002 | T7: =P7*(I7*5/J7+K7*L7+R7*(1-O7)*((1-M7)*F7+M7*S7)) -> 8722.2549
A8: Upside | B8: =Inputs!D5 -> 314 | C8: =Inputs!D6 -> 0.29 | D8: =Inputs!D7 -> 0.66 | E8: =Inputs!D8 -> 0.24 | F8: =Inputs!D9 -> 0.004 | G8: =Inputs!D10 -> 0.08 | H8: =Inputs!D11 -> 0.05 | I8: =Inputs!D12 -> 0.1 | J8: =Inputs!D13 -> 4000 | K8: =Inputs!D14 -> 0.1 | L8: =Inputs!D15 -> 0.0002 | M8: =Inputs!D16 -> 0.1 | N8: =Inputs!D17 -> 150000 | O8: =Inputs!D18 -> 0.02 | P8: =B8*C8*D8*(1+E8)*100000 -> 7452350.4 | Q8: =P8*F8 -> 29809.402 | R8: =MAX(0,1-G8-H8-I8-K8) -> 0.67 | S8: =MIN(F8,300/N8) -> 0.002 | T8: =P8*(I8*5/J8+K8*L8+R8*(1-O8)*((1-M8)*F8+M8*S8)) -> 19674.801
A9: Sensitivity (Base with one input changed)
A10: Share of P2M value above ₹2,000 — low | B10: =Inputs!B5 -> 314 | C10: =Inputs!B6 -> 0.29 | D10: 0.6 | E10: =Inputs!B8 -> 0.2 | F10: =Inputs!B9 -> 0.004 | G10: =Inputs!B10 -> 0.12 | H10: =Inputs!B11 -> 0.08 | I10: =Inputs!B12 -> 0.15 | J10: =Inputs!B13 -> 4000 | K10: =Inputs!B14 -> 0.15 | L10: =Inputs!B15 -> 0.0002 | M10: =Inputs!B16 -> 0.15 | N10: =Inputs!B17 -> 150000 | O10: =Inputs!B18 -> 0.05 | P10: =B10*C10*D10*(1+E10)*100000 -> 6556320 | Q10: =P10*F10 -> 26225.28 | R10: =MAX(0,1-G10-H10-I10-K10) -> 0.5 | S10: =MIN(F10,300/N10) -> 0.002 | T10: =P10*(I10*5/J10+K10*L10+R10*(1-O10)*((1-M10)*F10+M10*S10)) -> 12948.732
A11: Share of P2M value above ₹2,000 — high | B11: =Inputs!B5 -> 314 | C11: =Inputs!B6 -> 0.29 | D11: 0.72 | E11: =Inputs!B8 -> 0.2 | F11: =Inputs!B9 -> 0.004 | G11: =Inputs!B10 -> 0.12 | H11: =Inputs!B11 -> 0.08 | I11: =Inputs!B12 -> 0.15 | J11: =Inputs!B13 -> 4000 | K11: =Inputs!B14 -> 0.15 | L11: =Inputs!B15 -> 0.0002 | M11: =Inputs!B16 -> 0.15 | N11: =Inputs!B17 -> 150000 | O11: =Inputs!B18 -> 0.05 | P11: =B11*C11*D11*(1+E11)*100000 -> 7867584 | Q11: =P11*F11 -> 31470.336 | R11: =MAX(0,1-G11-H11-I11-K11) -> 0.5 | S11: =MIN(F11,300/N11) -> 0.002 | T11: =P11*(I11*5/J11+K11*L11+R11*(1-O11)*((1-M11)*F11+M11*S11)) -> 15538.478
A12: Exempt small-merchant share — low | B12: =Inputs!B5 -> 314 | C12: =Inputs!B6 -> 0.29 | D12: =Inputs!B7 -> 0.66 | E12: =Inputs!B8 -> 0.2 | F12: =Inputs!B9 -> 0.004 | G12: 0.06 | H12: =Inputs!B11 -> 0.08 | I12: =Inputs!B12 -> 0.15 | J12: =Inputs!B13 -> 4000 | K12: =Inputs!B14 -> 0.15 | L12: =Inputs!B15 -> 0.0002 | M12: =Inputs!B16 -> 0.15 | N12: =Inputs!B17 -> 150000 | O12: =Inputs!B18 -> 0.05 | P12: =B12*C12*D12*(1+E12)*100000 -> 7211952 | Q12: =P12*F12 -> 28847.808 | R12: =MAX(0,1-G12-H12-I12-K12) -> 0.56 | S12: =MIN(F12,300/N12) -> 0.002 | T12: =P12*(I12*5/J12+K12*L12+R12*(1-O12)*((1-M12)*F12+M12*S12)) -> 15764.606
A13: Exempt small-merchant share — high | B13: =Inputs!B5 -> 314 | C13: =Inputs!B6 -> 0.29 | D13: =Inputs!B7 -> 0.66 | E13: =Inputs!B8 -> 0.2 | F13: =Inputs!B9 -> 0.004 | G13: 0.2 | H13: =Inputs!B11 -> 0.08 | I13: =Inputs!B12 -> 0.15 | J13: =Inputs!B13 -> 4000 | K13: =Inputs!B14 -> 0.15 | L13: =Inputs!B15 -> 0.0002 | M13: =Inputs!B16 -> 0.15 | N13: =Inputs!B17 -> 150000 | O13: =Inputs!B18 -> 0.05 | P13: =B13*C13*D13*(1+E13)*100000 -> 7211952 | Q13: =P13*F13 -> 28847.808 | R13: =MAX(0,1-G13-H13-I13-K13) -> 0.42 | S13: =MIN(F13,300/N13) -> 0.002 | T13: =P13*(I13*5/J13+K13*L13+R13*(1-O13)*((1-M13)*F13+M13*S13)) -> 12215.604
A14: Capital-markets share — low | B14: =Inputs!B5 -> 314 | C14: =Inputs!B6 -> 0.29 | D14: =Inputs!B7 -> 0.66 | E14: =Inputs!B8 -> 0.2 | F14: =Inputs!B9 -> 0.004 | G14: =Inputs!B10 -> 0.12 | H14: =Inputs!B11 -> 0.08 | I14: =Inputs!B12 -> 0.15 | J14: =Inputs!B13 -> 4000 | K14: 0.08 | L14: =Inputs!B15 -> 0.0002 | M14: =Inputs!B16 -> 0.15 | N14: =Inputs!B17 -> 150000 | O14: =Inputs!B18 -> 0.05 | P14: =B14*C14*D14*(1+E14)*100000 -> 7211952 | Q14: =P14*F14 -> 28847.808 | R14: =MAX(0,1-G14-H14-I14-K14) -> 0.57 | S14: =MIN(F14,300/N14) -> 0.002 | T14: =P14*(I14*5/J14+K14*L14+R14*(1-O14)*((1-M14)*F14+M14*S14)) -> 15917.139
A15: Capital-markets share — high | B15: =Inputs!B5 -> 314 | C15: =Inputs!B6 -> 0.29 | D15: =Inputs!B7 -> 0.66 | E15: =Inputs!B8 -> 0.2 | F15: =Inputs!B9 -> 0.004 | G15: =Inputs!B10 -> 0.12 | H15: =Inputs!B11 -> 0.08 | I15: =Inputs!B12 -> 0.15 | J15: =Inputs!B13 -> 4000 | K15: 0.25 | L15: =Inputs!B15 -> 0.0002 | M15: =Inputs!B16 -> 0.15 | N15: =Inputs!B17 -> 150000 | O15: =Inputs!B18 -> 0.05 | P15: =B15*C15*D15*(1+E15)*100000 -> 7211952 | Q15: =P15*F15 -> 28847.808 | R15: =MAX(0,1-G15-H15-I15-K15) -> 0.4 | S15: =MIN(F15,300/N15) -> 0.002 | T15: =P15*(I15*5/J15+K15*L15+R15*(1-O15)*((1-M15)*F15+M15*S15)) -> 11852.843
A16: Essential-services share — low | B16: =Inputs!B5 -> 314 | C16: =Inputs!B6 -> 0.29 | D16: =Inputs!B7 -> 0.66 | E16: =Inputs!B8 -> 0.2 | F16: =Inputs!B9 -> 0.004 | G16: =Inputs!B10 -> 0.12 | H16: =Inputs!B11 -> 0.08 | I16: 0.08 | J16: =Inputs!B13 -> 4000 | K16: =Inputs!B14 -> 0.15 | L16: =Inputs!B15 -> 0.0002 | M16: =Inputs!B16 -> 0.15 | N16: =Inputs!B17 -> 150000 | O16: =Inputs!B18 -> 0.05 | P16: =B16*C16*D16*(1+E16)*100000 -> 7211952 | Q16: =P16*F16 -> 28847.808 | R16: =MAX(0,1-G16-H16-I16-K16) -> 0.57 | S16: =MIN(F16,300/N16) -> 0.002 | T16: =P16*(I16*5/J16+K16*L16+R16*(1-O16)*((1-M16)*F16+M16*S16)) -> 15387.06
A17: Essential-services share — high | B17: =Inputs!B5 -> 314 | C17: =Inputs!B6 -> 0.29 | D17: =Inputs!B7 -> 0.66 | E17: =Inputs!B8 -> 0.2 | F17: =Inputs!B9 -> 0.004 | G17: =Inputs!B10 -> 0.12 | H17: =Inputs!B11 -> 0.08 | I17: 0.25 | J17: =Inputs!B13 -> 4000 | K17: =Inputs!B14 -> 0.15 | L17: =Inputs!B15 -> 0.0002 | M17: =Inputs!B16 -> 0.15 | N17: =Inputs!B17 -> 150000 | O17: =Inputs!B18 -> 0.05 | P17: =B17*C17*D17*(1+E17)*100000 -> 7211952 | Q17: =P17*F17 -> 28847.808 | R17: =MAX(0,1-G17-H17-I17-K17) -> 0.4 | S17: =MIN(F17,300/N17) -> 0.002 | T17: =P17*(I17*5/J17+K17*L17+R17*(1-O17)*((1-M17)*F17+M17*S17)) -> 12610.098
A18: Rural and semi-urban share — low | B18: =Inputs!B5 -> 314 | C18: =Inputs!B6 -> 0.29 | D18: =Inputs!B7 -> 0.66 | E18: =Inputs!B8 -> 0.2 | F18: =Inputs!B9 -> 0.004 | G18: =Inputs!B10 -> 0.12 | H18: 0.04 | I18: =Inputs!B12 -> 0.15 | J18: =Inputs!B13 -> 4000 | K18: =Inputs!B14 -> 0.15 | L18: =Inputs!B15 -> 0.0002 | M18: =Inputs!B16 -> 0.15 | N18: =Inputs!B17 -> 150000 | O18: =Inputs!B18 -> 0.05 | P18: =B18*C18*D18*(1+E18)*100000 -> 7211952 | Q18: =P18*F18 -> 28847.808 | R18: =MAX(0,1-G18-H18-I18-K18) -> 0.54 | S18: =MIN(F18,300/N18) -> 0.002 | T18: =P18*(I18*5/J18+K18*L18+R18*(1-O18)*((1-M18)*F18+M18*S18)) -> 15257.606
A19: Rural and semi-urban share — high | B19: =Inputs!B5 -> 314 | C19: =Inputs!B6 -> 0.29 | D19: =Inputs!B7 -> 0.66 | E19: =Inputs!B8 -> 0.2 | F19: =Inputs!B9 -> 0.004 | G19: =Inputs!B10 -> 0.12 | H19: 0.14 | I19: =Inputs!B12 -> 0.15 | J19: =Inputs!B13 -> 4000 | K19: =Inputs!B14 -> 0.15 | L19: =Inputs!B15 -> 0.0002 | M19: =Inputs!B16 -> 0.15 | N19: =Inputs!B17 -> 150000 | O19: =Inputs!B18 -> 0.05 | P19: =B19*C19*D19*(1+E19)*100000 -> 7211952 | Q19: =P19*F19 -> 28847.808 | R19: =MAX(0,1-G19-H19-I19-K19) -> 0.44 | S19: =MIN(F19,300/N19) -> 0.002 | T19: =P19*(I19*5/J19+K19*L19+R19*(1-O19)*((1-M19)*F19+M19*S19)) -> 12722.605
A20: Share of standard value capped at ₹300 — low | B20: =Inputs!B5 -> 314 | C20: =Inputs!B6 -> 0.29 | D20: =Inputs!B7 -> 0.66 | E20: =Inputs!B8 -> 0.2 | F20: =Inputs!B9 -> 0.004 | G20: =Inputs!B10 -> 0.12 | H20: =Inputs!B11 -> 0.08 | I20: =Inputs!B12 -> 0.15 | J20: =Inputs!B13 -> 4000 | K20: =Inputs!B14 -> 0.15 | L20: =Inputs!B15 -> 0.0002 | M20: 0.08 | N20: =Inputs!B17 -> 150000 | O20: =Inputs!B18 -> 0.05 | P20: =B20*C20*D20*(1+E20)*100000 -> 7211952 | Q20: =P20*F20 -> 28847.808 | R20: =MAX(0,1-G20-H20-I20-K20) -> 0.5 | S20: =MIN(F20,300/N20) -> 0.002 | T20: =P20*(I20*5/J20+K20*L20+R20*(1-O20)*((1-M20)*F20+M20*S20)) -> 14723.2
A21: Share of standard value capped at ₹300 — high | B21: =Inputs!B5 -> 314 | C21: =Inputs!B6 -> 0.29 | D21: =Inputs!B7 -> 0.66 | E21: =Inputs!B8 -> 0.2 | F21: =Inputs!B9 -> 0.004 | G21: =Inputs!B10 -> 0.12 | H21: =Inputs!B11 -> 0.08 | I21: =Inputs!B12 -> 0.15 | J21: =Inputs!B13 -> 4000 | K21: =Inputs!B14 -> 0.15 | L21: =Inputs!B15 -> 0.0002 | M21: 0.25 | N21: =Inputs!B17 -> 150000 | O21: =Inputs!B18 -> 0.05 | P21: =B21*C21*D21*(1+E21)*100000 -> 7211952 | Q21: =P21*F21 -> 28847.808 | R21: =MAX(0,1-G21-H21-I21-K21) -> 0.5 | S21: =MIN(F21,300/N21) -> 0.002 | T21: =P21*(I21*5/J21+K21*L21+R21*(1-O21)*((1-M21)*F21+M21*S21)) -> 13558.47
A22: Leakage to other rails — low | B22: =Inputs!B5 -> 314 | C22: =Inputs!B6 -> 0.29 | D22: =Inputs!B7 -> 0.66 | E22: =Inputs!B8 -> 0.2 | F22: =Inputs!B9 -> 0.004 | G22: =Inputs!B10 -> 0.12 | H22: =Inputs!B11 -> 0.08 | I22: =Inputs!B12 -> 0.15 | J22: =Inputs!B13 -> 4000 | K22: =Inputs!B14 -> 0.15 | L22: =Inputs!B15 -> 0.0002 | M22: =Inputs!B16 -> 0.15 | N22: =Inputs!B17 -> 150000 | O22: 0 | P22: =B22*C22*D22*(1+E22)*100000 -> 7211952 | Q22: =P22*F22 -> 28847.808 | R22: =MAX(0,1-G22-H22-I22-K22) -> 0.5 | S22: =MIN(F22,300/N22) -> 0.002 | T22: =P22*(I22*5/J22+K22*L22+R22*(1-O22)*((1-M22)*F22+M22*S22)) -> 14910.711
A23: Leakage to other rails — high | B23: =Inputs!B5 -> 314 | C23: =Inputs!B6 -> 0.29 | D23: =Inputs!B7 -> 0.66 | E23: =Inputs!B8 -> 0.2 | F23: =Inputs!B9 -> 0.004 | G23: =Inputs!B10 -> 0.12 | H23: =Inputs!B11 -> 0.08 | I23: =Inputs!B12 -> 0.15 | J23: =Inputs!B13 -> 4000 | K23: =Inputs!B14 -> 0.15 | L23: =Inputs!B15 -> 0.0002 | M23: =Inputs!B16 -> 0.15 | N23: =Inputs!B17 -> 150000 | O23: 0.15 | P23: =B23*C23*D23*(1+E23)*100000 -> 7211952 | Q23: =P23*F23 -> 28847.808 | R23: =MAX(0,1-G23-H23-I23-K23) -> 0.5 | S23: =MIN(F23,300/N23) -> 0.002 | T23: =P23*(I23*5/J23+K23*L23+R23*(1-O23)*((1-M23)*F23+M23*S23)) -> 12909.394
A24: FY27 value growth — low | B24: =Inputs!B5 -> 314 | C24: =Inputs!B6 -> 0.29 | D24: =Inputs!B7 -> 0.66 | E24: 0.12 | F24: =Inputs!B9 -> 0.004 | G24: =Inputs!B10 -> 0.12 | H24: =Inputs!B11 -> 0.08 | I24: =Inputs!B12 -> 0.15 | J24: =Inputs!B13 -> 4000 | K24: =Inputs!B14 -> 0.15 | L24: =Inputs!B15 -> 0.0002 | M24: =Inputs!B16 -> 0.15 | N24: =Inputs!B17 -> 150000 | O24: =Inputs!B18 -> 0.05 | P24: =B24*C24*D24*(1+E24)*100000 -> 6731155.2 | Q24: =P24*F24 -> 26924.621 | R24: =MAX(0,1-G24-H24-I24-K24) -> 0.5 | S24: =MIN(F24,300/N24) -> 0.002 | T24: =P24*(I24*5/J24+K24*L24+R24*(1-O24)*((1-M24)*F24+M24*S24)) -> 13294.032
A25: FY27 value growth — high | B25: =Inputs!B5 -> 314 | C25: =Inputs!B6 -> 0.29 | D25: =Inputs!B7 -> 0.66 | E25: 0.28 | F25: =Inputs!B9 -> 0.004 | G25: =Inputs!B10 -> 0.12 | H25: =Inputs!B11 -> 0.08 | I25: =Inputs!B12 -> 0.15 | J25: =Inputs!B13 -> 4000 | K25: =Inputs!B14 -> 0.15 | L25: =Inputs!B15 -> 0.0002 | M25: =Inputs!B16 -> 0.15 | N25: =Inputs!B17 -> 150000 | O25: =Inputs!B18 -> 0.05 | P25: =B25*C25*D25*(1+E25)*100000 -> 7692748.8 | Q25: =P25*F25 -> 30770.995 | R25: =MAX(0,1-G25-H25-I25-K25) -> 0.5 | S25: =MIN(F25,300/N25) -> 0.002 | T25: =P25*(I25*5/J25+K25*L25+R25*(1-O25)*((1-M25)*F25+M25*S25)) -> 15193.179

Sheet Sensitivity
A1: Sensitivity: what moves the net pool most (Base)
A3: Driver | B3: Low input | C3: High input | D3: Net at low input (₹ crore) | E3: Net at high input (₹ crore) | F3: Swing (₹ crore) | G3: Rank
A4: Share of P2M value above ₹2,000 | B4: =Cases!D10 -> 0.6 | C4: =Cases!D11 -> 0.72 | D4: =Cases!T10 -> 12948.732 | E4: =Cases!T11 -> 15538.478 | F4: =ABS(E4-D4) -> 2589.7464 | G4: =RANK(F4,$F$4:$F$11) -> 4
A5: Exempt small-merchant share | B5: =Cases!G12 -> 0.06 | C5: =Cases!G13 -> 0.2 | D5: =Cases!T12 -> 15764.606 | E5: =Cases!T13 -> 12215.604 | F5: =ABS(E5-D5) -> 3549.0016 | G5: =RANK(F5,$F$4:$F$11) -> 2
A6: Capital-markets share | B6: =Cases!K14 -> 0.08 | C6: =Cases!K15 -> 0.25 | D6: =Cases!T14 -> 15917.139 | E6: =Cases!T15 -> 11852.843 | F6: =ABS(E6-D6) -> 4064.2955 | G6: =RANK(F6,$F$4:$F$11) -> 1
A7: Essential-services share | B7: =Cases!I16 -> 0.08 | C7: =Cases!I17 -> 0.25 | D7: =Cases!T16 -> 15387.06 | E7: =Cases!T17 -> 12610.098 | F7: =ABS(E7-D7) -> 2776.9621 | G7: =RANK(F7,$F$4:$F$11) -> 3
A8: Rural and semi-urban share | B8: =Cases!H18 -> 0.04 | C8: =Cases!H19 -> 0.14 | D8: =Cases!T18 -> 15257.606 | E8: =Cases!T19 -> 12722.605 | F8: =ABS(E8-D8) -> 2535.0011 | G8: =RANK(F8,$F$4:$F$11) -> 5
A9: Share of standard value capped at ₹300 | B9: =Cases!M20 -> 0.08 | C9: =Cases!M21 -> 0.25 | D9: =Cases!T20 -> 14723.2 | E9: =Cases!T21 -> 13558.47 | F9: =ABS(E9-D9) -> 1164.7302 | G9: =RANK(F9,$F$4:$F$11) -> 8
A10: Leakage to other rails | B10: =Cases!O22 -> 0 | C10: =Cases!O23 -> 0.15 | D10: =Cases!T22 -> 14910.711 | E10: =Cases!T23 -> 12909.394 | F10: =ABS(E10-D10) -> 2001.3167 | G10: =RANK(F10,$F$4:$F$11) -> 6
A11: FY27 value growth | B11: =Cases!E24 -> 0.12 | C11: =Cases!E25 -> 0.28 | D11: =Cases!T24 -> 13294.032 | E11: =Cases!T25 -> 15193.179 | F11: =ABS(E11-D11) -> 1899.1474 | G11: =RANK(F11,$F$4:$F$11) -> 7
A13: Base net pool (₹ crore) | D13: =Cases!T6 -> 14243.605
A14: Reading: the four segment-mix shares (who is exempt or on a special rate) move the answer more than growth or the cap. Those are what the primary research is designed to pin down.
